certpylot/__init__.py
certpylot/main.py
certpylot-0.1.1.dist-info/LICENSE
certpylot-0.1.1.dist-info/METADATA
certpylot-0.1.1.dist-info/WHEEL
certpylot-0.1.1.dist-info/RECORD
