Metadata-Version: 2.3
Name: certpylot
Version: 0.1.1
Summary: A Python library for managing SSL/TLS certificates with a focus on security and ease of use.
License: GPL-3.0
Author: Oliver Galbraith
Author-email: olivergalbraith0@gmail.com
Requires-Python: >=3.8,<4.0
Classifier: License :: OSI Approved :: GNU General Public License v3 (GPLv3)
Classifier: Programming Language :: Python :: 3
Classifier: Programming Language :: Python :: 3.8
Classifier: Programming Language :: Python :: 3.9
Classifier: Programming Language :: Python :: 3.10
Classifier: Programming Language :: Python :: 3.11
Classifier: Programming Language :: Python :: 3.12
Classifier: Programming Language :: Python :: 3.13
Requires-Dist: acme (>=2.0.0,<3.0.0)
Requires-Dist: cryptography (>=39.0.1,<40.0.0)
Project-URL: Documentation, https://github.com/ollie-galbraith/certpylot
Project-URL: Homepage, https://github.com/ollie-galbraith/certpylot
Project-URL: Repository, https://github.com/ollie-galbraith/certpylot
